interface/__init__.py
interface/compat.py
interface/default.py
interface/formatting.py
interface/functional.py
interface/interface.py
interface/typecheck.py
interface/typed_signature.py
interface/utils.py
interface/tests/__init__.py
interface/tests/_py3_typecheck_tests.py
interface/tests/test_functional.py
interface/tests/test_interface.py
interface/tests/test_typecheck.py
interface/tests/test_utils.py
python_interface-1.4.0.dist-info/DESCRIPTION.rst
python_interface-1.4.0.dist-info/METADATA
python_interface-1.4.0.dist-info/RECORD
python_interface-1.4.0.dist-info/WHEEL
python_interface-1.4.0.dist-info/metadata.json
python_interface-1.4.0.dist-info/top_level.txt
