Metadata-Version: 1.1
Name: python-interface
Version: 1.4.0
Summary: Pythonic Interface definitions
Home-page: https://github.com/ssanderson/interface
Author: Scott Sanderson
Author-email: scott.b.sanderson90@gmail.com
License: Apache 2.0
Platform: UNKNOWN
Classifier: Development Status :: 5 - Production/Stable
Classifier: License :: OSI Approved :: Apache Software License
Classifier: Natural Language :: English
Classifier: Programming Language :: Python :: 2.7
Classifier: Programming Language :: Python :: 3.4
Classifier: Programming Language :: Python :: 3.5
Classifier: Topic :: Software Development :: Pre-processors
